tacty/__init__.py
tacty/command_bus.py
tacty/exception/__init__.py
tacty/handler/__init__.py
tacty/middleware/__init__.py
tacty/resolver/__init__.py
tests/__init__.py
tests/test_command_bus.py
tests/middleware/__init__.py
tests/middleware/test_command_handler_middleware.py
tests/resolver/__init__.py
tests/resolver/test_in_memory_resolver.py
tacty-1.1.0.dist-info/LICENSE
tacty-1.1.0.dist-info/METADATA
tacty-1.1.0.dist-info/WHEEL
tacty-1.1.0.dist-info/top_level.txt
tacty-1.1.0.dist-info/RECORD
