Metadata-Version: 2.1
Name: tacty
Version: 1.1.0
Summary: An extensible command bus for Python 3
Home-page: https://github.com/cristiangsp/tacty
Author: Cristian Gonzalez
Author-email: cristian.gsp@gmail.com
License: UNKNOWN
Platform: UNKNOWN
Classifier: Programming Language :: Python :: 3.6
Classifier: License :: OSI Approved :: GNU General Public License v3 (GPLv3)
Classifier: Operating System :: OS Independent
Requires-Python: >=3.6
